[{"Points":0,"Name":"Bann der Keule","Characteristic":"","Type":"Knochenkeule","Cost":0,"Reqirements":null,"Max":3},{"Points":0,"Name":"Geist der Keule","Characteristic":"","Type":"Knochenkeule","Cost":0,"Reqirements":null,"Max":1},{"Points":0,"Name":"Gesp\u00FCr der Keule","Characteristic":"","Type":"Knochenkeule","Cost":0,"Reqirements":null,"Max":0},{"Points":0,"Name":"Gesp\u00FCr der Keule","Characteristic":"","Type":"Knochenkeule","Cost":0,"Reqirements":null,"Max":0},{"Points":0,"Name":"Hilfe der Keule","Characteristic":"","Type":"Knochenkeule","Cost":0,"Reqirements":null,"Max":3},{"Points":0,"Name":"Kraft der Keule","Characteristic":"","Type":"Knochenkeule","Cost":0,"Reqirements":null,"Max":0},{"Points":0,"Name":"N\u00E4he zur Natur","Characteristic":"","Type":"Knochenkeule","Cost":0,"Reqirements":null,"Max":3},{"Points":0,"Name":"Opferkeule","Characteristic":"","Type":"Knochenkeule","Cost":0,"Reqirements":null,"Max":1},{"Points":0,"Name":"Zauber der Keule","Characteristic":"","Type":"Knochenkeule","Cost":0,"Reqirements":null,"Max":3},{"Points":0,"Name":"Apport","Characteristic":"","Type":"Knochenkeule","Cost":1,"Reqirements":null,"Max":1}]